ordeq_ibis/__init__.py
ordeq_ibis/_version.py
ordeq_ibis/py.typed
ordeq_ibis/io/__init__.py
ordeq_ibis/io/csv.py
ordeq_ibis/io/delta.py
ordeq_ibis/io/json.py
ordeq_ibis/io/parquet.py
ordeq_ibis/io/sql.py
ordeq_ibis/io/table.py
ordeq_ibis/io/view.py
ordeq_ibis/io/xlsx.py
ordeq_ibis-1.0.1.dist-info/licenses/LICENSE
ordeq_ibis-1.0.1.dist-info/METADATA
ordeq_ibis-1.0.1.dist-info/WHEEL
ordeq_ibis-1.0.1.dist-info/top_level.txt
ordeq_ibis-1.0.1.dist-info/RECORD
